mongo_log/__init__.py
mongo_log/models.py
mongo_log-0.0.4.dist-info/METADATA
mongo_log-0.0.4.dist-info/WHEEL
mongo_log-0.0.4.dist-info/top_level.txt
mongo_log-0.0.4.dist-info/RECORD
